{
  "project_info": {
    "project_number": "619352328087",
    "project_id": "e-commerce-3f257",
    "storage_bucket": "e-commerce-3f257.firebasestorage.app"
  },
  "client": [
    {
      "client_info": {
        "mobilesdk_app_id": "1:619352328087:android:c17d7e9fa99f7dfccb26d2",
        "android_client_info": {
          "package_name": "com.example.ecommerce"
        }
      },
      "oauth_client": [],
      "api_key": [
        {
          "current_key": "AIzaSyBFWVEvUEWjYMyFl8gHBx8k6bkes9hW7DI"
        }
      ],
      "services": {
        "appinvite_service": {
          "other_platform_oauth_client": []
        }
      }
    }
  ],
  "configuration_version": "1"
}